odoo/addons/l10n_it_sdd_cbi/README.rst
odoo/addons/l10n_it_sdd_cbi/__init__.py
odoo/addons/l10n_it_sdd_cbi/__manifest__.py
odoo/addons/l10n_it_sdd_cbi/post_install.py
odoo/addons/l10n_it_sdd_cbi/data/CBIBdySDDReq.00.01.00.xsd
odoo/addons/l10n_it_sdd_cbi/data/CBIBdySDDReq.00.01.01.xsd
odoo/addons/l10n_it_sdd_cbi/data/CBISDDReqLogMsg.00.01.00.xsd
odoo/addons/l10n_it_sdd_cbi/data/CBISDDReqLogMsg.00.01.01.xsd
odoo/addons/l10n_it_sdd_cbi/data/account_payment_method.xml
odoo/addons/l10n_it_sdd_cbi/i18n/it.po
odoo/addons/l10n_it_sdd_cbi/i18n/l10n_it_sdd_cbi.pot
odoo/addons/l10n_it_sdd_cbi/models/__init__.py
odoo/addons/l10n_it_sdd_cbi/models/account_payment_line.py
odoo/addons/l10n_it_sdd_cbi/models/account_payment_method.py
odoo/addons/l10n_it_sdd_cbi/models/account_payment_order.py
odoo/addons/l10n_it_sdd_cbi/models/res_company.py
odoo/addons/l10n_it_sdd_cbi/models/res_config_settings.py
odoo/addons/l10n_it_sdd_cbi/readme/CONTRIBUTORS.rst
odoo/addons/l10n_it_sdd_cbi/readme/DESCRIPTION.rst
odoo/addons/l10n_it_sdd_cbi/static/description/icon.png
odoo/addons/l10n_it_sdd_cbi/static/description/index.html
odoo/addons/l10n_it_sdd_cbi/views/account_payment_order_view.xml
odoo/addons/l10n_it_sdd_cbi/views/res_config_settings_view.xml
odoo14_addon_l10n_it_sdd_cbi-14.0.1.0.1.dist-info/METADATA
odoo14_addon_l10n_it_sdd_cbi-14.0.1.0.1.dist-info/WHEEL
odoo14_addon_l10n_it_sdd_cbi-14.0.1.0.1.dist-info/top_level.txt
odoo14_addon_l10n_it_sdd_cbi-14.0.1.0.1.dist-info/RECORD
