Metadata-Version: 2.1
Name: odoo14-addon-l10n_it_sdd_cbi
Version: 14.0.1.0.1
Summary: Create SEPA files for CBI SDD Italy
Home-page: https://github.com/OCA/l10n-italy
Author: Dinamiche Aziendali srl, Odoo Community Association (OCA)
Author-email: support@odoo-community.org
License: AGPL-3
Classifier: Programming Language :: Python
Classifier: Framework :: Odoo
Classifier: Framework :: Odoo :: 14.0
Classifier: License :: OSI Approved :: GNU Affero General Public License v3
Classifier: Development Status :: 4 - Beta
Requires-Python: >=3.6
Requires-Dist: odoo14-addon-account-banking-mandate
Requires-Dist: odoo14-addon-account-banking-pain-base
Requires-Dist: odoo14-addon-account-banking-sepa-direct-debit
Requires-Dist: odoo14-addon-account-payment-order
Requires-Dist: odoo14-addon-l10n-it-abicab
Requires-Dist: odoo<14.1dev,>=14.0a
